[
  {
    "textPl": "Czy ze względów bezpieczeństwa wskazane jest, aby używając gaśnicy samochodowej, unikać pełnego otwarcia pokrywy komory silnika?",
    "textUz": "Xavfsizlik nuqtai nazaridan, avtomobil o't o'chirgichidan foydalanganda dvigatel qopqog'ini to'liq ochishdan saqlanish tavsiya etiladimi?",
    "category": "Umumiy qoidalar",
    "isPremium": true,
    "mediaFileName": "R_2org.mp4",
    "mediaType": "video",
    "options": [
      {
        "textPl": "Tak",
        "textUz": "Ha",
        "isCorrect": true
      },
      {
        "textPl": "Nie",
        "textUz": "Yo'q",
        "isCorrect": false
      }
    ]
  },
  {
    "textPl": "Czy w tej sytuacji uzasadnione jest sprawdzenie, czy sprawca wypadku zaciągnął hamulec awaryjny i wyłączył silnik?",
    "textUz": "Bu vaziyatda baxtsiz hodisa aybdori qo'l tormozini tortganini va dvigatelni o'chirganini tekshirish asoslimi?",
    "category": "Umumiy qoidalar",
    "isPremium": true,
    "mediaFileName": "R_1org.mp4",
    "mediaType": "video",
    "options": [
      {
        "textPl": "Tak",
        "textUz": "Ha",
        "isCorrect": true
      },
      {
        "textPl": "Nie",
        "textUz": "Yo'q",
        "isCorrect": false
      }
    ]
  },
  {
    "textPl": "Czy kierując pojazdem w stanie pobudzenia emocjonalnego, zwiększasz precyzję i trafność swoich reakcji w sytuacji niebezpiecznej?",
    "textUz": "Hissiy qo'zg'algan holatda transport vositasini boshqarganda, xavfli vaziyatda reaksiyalaringizning aniqligi oshadimi?",
    "category": "Umumiy qoidalar",
    "isPremium": true,
    "mediaFileName": "W20(31).mp4",
    "mediaType": "video",
    "options": [
      {
        "textPl": "Tak",
        "textUz": "Ha",
        "isCorrect": false
      },
      {
        "textPl": "Nie",
        "textUz": "Yo'q",
        "isCorrect": true
      }
    ]
  },
  {
    "textPl": "Czy w tej sytuacji masz prawo wyprzedzić tramwaj?",
    "textUz": "Bu vaziyatda tramvaydan o'zib o'tish huquqingiz bormi?",
    "category": "O'zib o'tish",
    "isPremium": true,
    "mediaFileName": "W12(174).mp4",
    "mediaType": "video",
    "options": [
      {
        "textPl": "Tak",
        "textUz": "Ha",
        "isCorrect": true
      },
      {
        "textPl": "Nie",
        "textUz": "Yo'q",
        "isCorrect": false
      }
    ]
  }
]